{
"Perfect Match":[
 {
  "شرح": "انتقال وجه از سپرده 4001003637078قرض الحسنه جاري بدون دسته چک احمدرضا\/نوروزي فرد\/ابراهيم به سپرده700831655066 صندوق سرمايه گذاري امين آشنا ايرانيان احمدرضا نوروزي فرد، کد ملي 2283028515",
  "تاریخ": "1403\/02\/01",
  "زمان": "13:53:28",
  "واریز": 88500000000,
  "برداشت": 0,
  "موجودی": 103130763146,
  "شعبه عامل": "مرکزی شیراز(270)",
  "شماره سند": 7594453691,
  "نام": "احمدرضا",
  "نام خانوادگی": "نوروزي فرد",
  "نام پدر": "ابراهيم",
  "کد ملی": "2283028515",
  "سایر": 0,
  "حساب": 4001003637078,
  "*": "*",
  "*": "*",
  "*": "*",
  "شماره": "82721042",
  "کد تفصیل": 1163950,
  "نام": "احمدرضا",
  "نام خانوادگی": "نوروزي فرد",
  "کد ملی": "2283028515",
  "حساب": 3499418943,
  "نوع": "صدور",
  "مبلغ": 88500000000,
  "تاریخ درخواست": "1403\/02\/01",
  "زمان": "13:54",
  "شماره فیش": 98924066,
  " شماره شبا": "IR580120020000003499418943"
 },
 {
  "شرح": "انتقال وجه از سپرده 4001003283432قرض الحسنه جاري بدون دسته چک ابوالفضل\/ذوالفقاري\/اصغر به سپرده700831655066 صندوق سرمايه گذاري امين آشنا ايرانيان ابوالفضل ذوالفقاري 0603350631",
  "تاریخ": "1403\/02\/01",
  "زمان": "11:24:28",
  "واریز": 49250000000,
  "برداشت": 0,
  "موجودی": 128798943146,
  "شعبه عامل": "ساوه (استان مرکزی)(430)",
  "شماره سند": 7593756498,
  "نام": "ابوالفضل",
  "نام خانوادگی": "ذوالفقاري",
  "نام پدر": "اصغر",
  "کد ملی": "0603350631",
  "سایر": 0,
  "حساب": 4001003283432,
  "*": "*",
  "*": "*",
  "*": "*",
  "شماره": "82713206",
  "کد تفصیل": 1161673,
  "نام": "ابوالفضل",
  "نام خانوادگی": "ذوالفقاري",
  "کد ملی": "0603350631",
  "حساب": 4001003283432,
  "نوع": "صدور",
  "مبلغ": 49250000000,
  "تاریخ درخواست": "1403\/02\/01",
  "زمان": "10:32",
  "شماره فیش": 95414989,
  " شماره شبا": "IR710610000004001003283432"
 },
 {
  "شرح": "انتقال وجه از سپرده 7001000454068سپرده سرمايه گذاري عادي صمد\/درمانلو\/علي اکبر به سپرده700831655066 صندوق سرمايه گذاري امين آشنا ايرانيان صمد درمانلو 0601084292",
  "تاریخ": "1403\/02\/01",
  "زمان": "15:08:05",
  "واریز": 49000000000,
  "برداشت": 0,
  "موجودی": 68033353146,
  "شعبه عامل": "ساوه (استان مرکزی)(430)",
  "شماره سند": 7594739428,
  "نام": "صمد",
  "نام خانوادگی": "درمانلو",
  "نام پدر": "علي اکبر",
  "کد ملی": "0601084292",
  "سایر": 0,
  "حساب": 7001000454068,
  "*": "*",
  "*": "*",
  "*": "*",
  "شماره": "82722484",
  "کد تفصیل": 1163951,
  "نام": "صمد",
  "نام خانوادگی": "درمانلو",
  "کد ملی": "0601084292",
  "حساب": 102446195005,
  "نوع": "صدور",
  "مبلغ": 49000000000,
  "تاریخ درخواست": "1403\/02\/01",
  "زمان": "15:01",
  "شماره فیش": 97084710,
  " شماره شبا": "IR620190000000102446195005"
 },
 {
  "شرح": "انتقال وجه از سپرده 4001001681584قرض الحسنه جاري بدون دسته چک عليرضا\/جوکار\/مهدي به سپرده700831655066 صندوق سرمايه گذاري امين آشنا ايرانيان 2283631270عليرضا جوکار",
  "تاریخ": "1403\/02\/01",
  "زمان": "11:08:37",
  "واریز": 40629000000,
  "برداشت": 0,
  "موجودی": 78264443146,
  "شعبه عامل": "پایانه کاراندیش شیراز(315)",
  "شماره سند": 7593686600,
  "نام": "عليرضا",
  "نام خانوادگی": "جوکار",
  "نام پدر": "مهدي",
  "کد ملی": "2283631270",
  "سایر": 0,
  "حساب": 4001001681584,
  "*": "*",
  "*": "*",
  "*": "*",
  "شماره": "82713756",
  "کد تفصیل": 1163833,
  "نام": "عليرضا",
  "نام خانوادگی": "جوكار ",
  "کد ملی": "2283631270",
  "حساب": 4001001681584,
  "نوع": "صدور",
  "مبلغ": 40629000000,
  "تاریخ درخواست": "1403\/02\/01",
  "زمان": "11:11",
  "شماره فیش": 96041710,
  " شماره شبا": "IR920610000004001001681584"
 },
 {
  "شرح": "انتقال وجه از سپرده 700824831591سپرده سرمايه گذاري عادي علي\/اميري\/قربانعلي به سپرده700831655066 صندوق سرمايه گذاري امين آشنا ايرانيان علي اميري 0638955777",
  "تاریخ": "1403\/02\/01",
  "زمان": "14:01:41",
  "واریز": 18000000000,
  "برداشت": 0,
  "موجودی": 123284263146,
  "شعبه عامل": "بلوار امامت(541)",
  "شماره سند": 7594487598,
  "نام": "علي",
  "نام خانوادگی": "اميري",
  "نام پدر": "قربانعلي",
  "کد ملی": "0638955777",
  "سایر": 0,
  "حساب": 700824831591,
  "*": "*",
  "*": "*",
  "*": "*",
  "شماره": "82724985",
  "کد تفصیل": 1163954,
  "نام": "علي",
  "نام خانوادگی": "اميري",
  "کد ملی": "0638955777",
  "حساب": 700824831591,
  "نوع": "صدور",
  "مبلغ": 18000000000,
  "تاریخ درخواست": "1403\/02\/01",
  "زمان": "15:42",
  "شماره فیش": 890617,
  " شماره شبا": "IR500120000000000009188588"
 },
 {
  "شرح": "انتقال وجه از سپرده 100837763696سپرده قرض الحسنه جاري (بدون دسته چک) محمود\/نصيرپور\/محمد به سپرده700831655066 صندوق سرمايه گذاري امين آشنا ايرانيان محمودنصيرپور2370370076",
  "تاریخ": "1403\/02\/01",
  "زمان": "13:06:39",
  "واریز": 6500000000,
  "برداشت": 0,
  "موجودی": 12328763146,
  "شعبه عامل": "باجه کازرون(3153)",
  "شماره سند": 7594255460,
  "نام": "محمود",
  "نام خانوادگی": "نصيرپور",
  "نام پدر": "محمد",
  "کد ملی": "2370370076",
  "سایر": 0,
  "حساب": 100837763696,
  "*": "*",
  "*": "*",
  "*": "*",
  "شماره": "82717990",
  "کد تفصیل": 1160643,
  "نام": "محمود",
  "نام خانوادگی": "نصير پور",
  "کد ملی": "2370370076",
  "حساب": 100837763696,
  "نوع": "صدور",
  "مبلغ": 6500000000,
  "تاریخ درخواست": "1403\/02\/01",
  "زمان": "13:10",
  "شماره فیش": 95418675,
  " شماره شبا": "IR820610000000100837763696"
 },
 {
  "شرح": "انتقال وجه از سپرده 4001001548570قرض الحسنه جاري بدون دسته چک مهدي\/مريدي\/قربانعلي به سپرده700831655066 صندوق سرمايه گذاري امين آشنا ايرانيان مهدي مريدي 0943414938",
  "تاریخ": "1403\/02\/01",
  "زمان": "15:36:55",
  "واریز": 6400000000,
  "برداشت": 0,
  "موجودی": 74513353146,
  "شعبه عامل": "بلوار امامت(541)",
  "شماره سند": 7594823170,
  "نام": "مهدي",
  "نام خانوادگی": "مريدي",
  "نام پدر": "قربانعلي",
  "کد ملی": "0943414938",
  "سایر": 0,
  "حساب": 4001001548570,
  "*": "*",
  "*": "*",
  "*": "*",
  "شماره": "82723074",
  "کد تفصیل": 1160787,
  "نام": "مهدي",
  "نام خانوادگی": "مريدي",
  "کد ملی": "0943414938",
  "حساب": 4001001548570,
  "نوع": "صدور",
  "مبلغ": 6400000000,
  "تاریخ درخواست": "1403\/02\/01",
  "زمان": "15:34",
  "شماره فیش": 890917,
  " شماره شبا": "IR450610000004001001548570"
 },
 {
  "شرح": "انتقال وجه از سپرده 4001003645543قرض الحسنه جاري بدون دسته چک مجتبي\/حسيني\/علي به سپرده700831655066 صندوق سرمايه گذاري امين آشنا ايرانيان مجتبي حسيني 3621637028",
  "تاریخ": "1403\/02\/01",
  "زمان": "10:21:59",
  "واریز": 5250000000,
  "برداشت": 0,
  "موجودی": 25585443146,
  "شعبه عامل": "بلوار امامت(541)",
  "شماره سند": 7593489490,
  "نام": "مجتبي",
  "نام خانوادگی": "حسيني",
  "نام پدر": "علي",
  "کد ملی": "3621637028",
  "سایر": 0,
  "حساب": 4001003645543,
  "*": "*",
  "*": "*",
  "*": "*",
  "شماره": "82713061",
  "کد تفصیل": 1163917,
  "نام": "مجتبي",
  "نام خانوادگی": "حسيني",
  "کد ملی": "3621637028",
  "حساب": 111603571002,
  "نوع": "صدور",
  "مبلغ": 5250000000,
  "تاریخ درخواست": "1403\/02\/01",
  "زمان": "10:20",
  "شماره فیش": 556776,
  " شماره شبا": "IR040170000000111603571002"
 },
 {
  "شرح": "انتقال وجه از سپرده 4001003546935قرض الحسنه جاري بدون دسته چک مهدي\/نجف زاده استاد\/علي اکبر به سپرده700831655066 صندوق سرمايه گذاري امين آشنا ايرانيان مهدي نجف زاده استاد 0938997483",
  "تاریخ": "1403\/02\/01",
  "زمان": "14:17:31",
  "واریز": 5000000000,
  "برداشت": 0,
  "موجودی": 130809763146,
  "شعبه عامل": "باجه الهیه مشهد(3963)",
  "شماره سند": 7594558745,
  "نام": "مهدي",
  "نام خانوادگی": "نجف زاده استاد",
  "نام پدر": "علي اکبر",
  "کد ملی": "0938997483",
  "سایر": 0,
  "حساب": 4001003546935,
  "*": "*",
  "*": "*",
  "*": "*",
  "شماره": "82721278",
  "کد تفصیل": 1159053,
  "نام": "مهدي ",
  "نام خانوادگی": "نجف زاده استاد",
  "کد ملی": "0938997483",
  "حساب": 700830139815,
  "نوع": "صدور",
  "مبلغ": 5000000000,
  "تاریخ درخواست": "1403\/02\/01",
  "زمان": "14:16",
  "شماره فیش": 567074,
  " شماره شبا": "IR680610000000700830139815"
 },
 {
  "شرح": "انتقال وجه از سپرده 4001003627414قرض الحسنه جاري بدون دسته چک سميه\/مولائي\/حسن به سپرده700831655066 صندوق سرمايه گذاري امين آشنا ايرانيان سميه مولائي کد ملي 2300464195 شماره فيش 94991259",
  "تاریخ": "1403\/02\/01",
  "زمان": "10:30:14",
  "واریز": 5000000000,
  "برداشت": 0,
  "موجودی": 30585443146,
  "شعبه عامل": "جهرم(4562)",
  "شماره سند": 7593522892,
  "نام": "سميه",
  "نام خانوادگی": "مولائي",
  "نام پدر": "حسن",
  "کد ملی": "2300464195",
  "سایر": "94991259",
  "حساب": 4001003627414,
  "*": "*",
  "*": "*",
  "*": "*",
  "شماره": "82713255",
  "کد تفصیل": 1163931,
  "نام": "سميه",
  "نام خانوادگی": "مولايي",
  "کد ملی": "2300464195",
  "حساب": 4001003627414,
  "نوع": "صدور",
  "مبلغ": 5000000000,
  "تاریخ درخواست": "1403\/02\/01",
  "زمان": "10:34",
  "شماره فیش": 94991259,
  " شماره شبا": "IR160610000004001003627414"
 },
 {
  "شرح": "انتقال وجه از سپرده 7001000620514سپرده سرمايه گذاري عادي داود\/علي ياري\/سهلعلي به سپرده700831655066 صندوق سرمايه گذاري امين آشنا ايرانيان داودعلي ياري 0602649056",
  "تاریخ": "1403\/02\/01",
  "زمان": "09:03:09",
  "واریز": 4788000000,
  "برداشت": 0,
  "موجودی": 15330443146,
  "شعبه عامل": "ساوه (استان مرکزی)(430)",
  "شماره سند": 7593207176,
  "نام": "داود",
  "نام خانوادگی": "علي ياري",
  "نام پدر": "سهلعلي",
  "کد ملی": "0602649056",
  "سایر": 0,
  "حساب": 7001000620514,
  "*": "*",
  "*": "*",
  "*": "*",
  "شماره": "82711067",
  "کد تفصیل": 1163918,
  "نام": "داود ",
  "نام خانوادگی": "علي ياري",
  "کد ملی": "0602649056",
  "حساب": 7001000620514,
  "نوع": "صدور",
  "مبلغ": 4788000000,
  "تاریخ درخواست": "1403\/02\/01",
  "زمان": "08:40",
  "شماره فیش": 97084487,
  " شماره شبا": "IR560610000007001000620514"
 },
 {
  "شرح": "انتقال وجه از سپرده 100841607194سپرده قرض الحسنه جاري (بدون دسته چک) آذر\/تولايي\/اکبر به سپرده700831655066 صندوق سرمايه گذاري امين آشنا ايرانيان 2298899134آذر تولائي",
  "تاریخ": "1403\/02\/01",
  "زمان": "09:52:34",
  "واریز": 4465000000,
  "برداشت": 0,
  "موجودی": 20335443146,
  "شعبه عامل": "پایانه کاراندیش شیراز(315)",
  "شماره سند": 7593378964,
  "نام": "آذر",
  "نام خانوادگی": "تولايي",
  "نام پدر": "اکبر",
  "کد ملی": "2298899134",
  "سایر": 0,
  "حساب": 100841607194,
  "*": "*",
  "*": "*",
  "*": "*",
  "شماره": "82712440",
  "کد تفصیل": 1163923,
  "نام": "آذر",
  "نام خانوادگی": "تولائي",
  "کد ملی": "2298899134",
  "حساب": 8146454703,
  "نوع": "صدور",
  "مبلغ": 4465000000,
  "تاریخ درخواست": "1403\/02\/01",
  "زمان": "09:44",
  "شماره فیش": 97549687,
  " شماره شبا": "IR660120010000008146454703"
 },
 {
  "شرح": "انتقال وجه از سپرده 4001003616694سپرده قرض الحسنه پس انداز (حقيقي) سيدابوالفضل\/حسيني\/سيدقاسم به سپرده700831655066 صندوق سرمايه گذاري امين آشنا ايرانيان سيدابوالفضل حسيني کدملي: 5749127796",
  "تاریخ": "1403\/02\/01",
  "زمان": "08:03:22",
  "واریز": 4400000000,
  "برداشت": 0,
  "موجودی": 8142443146,
  "شعبه عامل": "قاسم آباد(396)",
  "شماره سند": 7593028130,
  "نام": "سيدابوالفضل",
  "نام خانوادگی": "حسيني",
  "نام پدر": "سيدقاسم",
  "کد ملی": "5749127796",
  "سایر": 0,
  "حساب": 4001003616694,
  "*": "*",
  "*": "*",
  "*": "*",
  "شماره": "82710274",
  "کد تفصیل": 1163449,
  "نام": "سيد ابوالفضل ",
  "نام خانوادگی": "حسيني ",
  "کد ملی": "5749127796",
  "حساب": 8125587937,
  "نوع": "صدور",
  "مبلغ": 4400000000,
  "تاریخ درخواست": "1403\/02\/01",
  "زمان": "08:01",
  "شماره فیش": 103685011,
  " شماره شبا": "IR480120020000008125587937"
 },
 {
  "شرح": "انتقال وجه از سپرده 7001003646549سپرده سرمايه گذاري عادي علي\/اميري\/کوروش به سپرده700831655066 صندوق سرمايه گذاري امين آشنا ايرانيان علي اميري2282741536",
  "تاریخ": "1403\/02\/01",
  "زمان": "14:33:27",
  "واریز": 4326000000,
  "برداشت": 0,
  "موجودی": 144536363146,
  "شعبه عامل": "پایانه کاراندیش شیراز(315)",
  "شماره سند": 7594627146,
  "نام": "علي",
  "نام خانوادگی": "اميري",
  "نام پدر": "کوروش",
  "کد ملی": "2282741536",
  "سایر": 0,
  "حساب": 7001003646549,
  "*": "*",
  "*": "*",
  "*": "*",
  "شماره": "82721377",
  "کد تفصیل": 1163927,
  "نام": "علي",
  "نام خانوادگی": "اميري",
  "کد ملی": "2282741536",
  "حساب": 355595601000,
  "نوع": "صدور",
  "مبلغ": 4326000000,
  "تاریخ درخواست": "1403\/02\/01",
  "زمان": "14:26",
  "شماره فیش": 96041711,
  " شماره شبا": "IR980170000000355595601000"
 },
 {
  "شرح": "انتقال وجه از سپرده 400819073558قرض الحسنه جاري بدون دسته چک فاطمه\/احمدي\/علي اکبر به سپرده700831655066 صندوق سرمايه گذاري امين آشنا ايرانيان فاطمه احمدي0730852563",
  "تاریخ": "1403\/02\/01",
  "زمان": "14:20:44",
  "واریز": 3800000000,
  "برداشت": 0,
  "موجودی": 134609763146,
  "شعبه عامل": "مصلی مشهد(304)",
  "شماره سند": 7594570853,
  "نام": "فاطمه",
  "نام خانوادگی": "احمدي",
  "نام پدر": "علي اکبر",
  "کد ملی": "0730852563",
  "سایر": 0,
  "حساب": 400819073558,
  "*": "*",
  "*": "*",
  "*": "*",
  "شماره": "82721282",
  "کد تفصیل": 1163953,
  "نام": "فاطمه",
  "نام خانوادگی": "احمدي",
  "کد ملی": "0730852563",
  "حساب": 21594660007,
  "نوع": "صدور",
  "مبلغ": 3800000000,
  "تاریخ درخواست": "1403\/02\/01",
  "زمان": "14:17",
  "شماره فیش": 102818522,
  " شماره شبا": "IR920190000000215946640007"
 },
 {
  "شرح": "انتقال وجه از سپرده 7001000870822سپرده سرمايه گذاري عادي حامد\/اميرآبي\/عباس به سپرده700831655066 صندوق سرمايه گذاري امين آشنا ايرانيان 0603325238حامد اميرآبي",
  "تاریخ": "1403\/02\/01",
  "زمان": "10:37:39",
  "واریز": 3000000000,
  "برداشت": 0,
  "موجودی": 33585443146,
  "شعبه عامل": "ساوه (استان مرکزی)(430)",
  "شماره سند": 7593553353,
  "نام": "حامد",
  "نام خانوادگی": "اميرآبي",
  "نام پدر": "عباس",
  "کد ملی": "0603325238",
  "سایر": 0,
  "حساب": 7001000870822,
  "*": "*",
  "*": "*",
  "*": "*",
  "شماره": "82713261",
  "کد تفصیل": 1163835,
  "نام": "حامد",
  "نام خانوادگی": "اميرآبي",
  "کد ملی": "0603325238",
  "حساب": 7001000870822,
  "نوع": "صدور",
  "مبلغ": 3000000000,
  "تاریخ درخواست": "1403\/02\/01",
  "زمان": "10:35",
  "شماره فیش": 95001531,
  " شماره شبا": "IR110150000105170277060781"
 },
 {
  "شرح": "انتقال وجه از سپرده 4001003544435قرض الحسنه جاري بدون دسته چک محمدرضا\/علي پور\/محمدعلي به سپرده700831655066 صندوق سرمايه گذاري امين آشنا ايرانيان محمد رضا علي پور ش م0888425414شعبه بيرجند306",
  "تاریخ": "1403\/02\/01",
  "زمان": "14:14:34",
  "واریز": 2500000000,
  "برداشت": 0,
  "موجودی": 125809763146,
  "شعبه عامل": "بیرجند(306)",
  "شماره سند": 7594547874,
  "نام": "محمدرضا",
  "نام خانوادگی": "علي پور",
  "نام پدر": "محمدعلي",
  "کد ملی": "0888425414",
  "سایر": "306",
  "حساب": 4001003544435,
  "*": "*",
  "*": "*",
  "*": "*",
  "شماره": "82721520",
  "کد تفصیل": 1163959,
  "نام": "محمدرضا",
  "نام خانوادگی": "علي پور",
  "کد ملی": "0888425414",
  "حساب": 103104473006,
  "نوع": "صدور",
  "مبلغ": 2500000000,
  "تاریخ درخواست": "1403\/02\/01",
  "زمان": "14:34",
  "شماره فیش": 77122687,
  " شماره شبا": "IR200170000000103104473006"
 },
 {
  "شرح": "انتقال وجه از سپرده 4001003642761سپرده قرض الحسنه پس انداز (حقيقي) حميدرضا\/ذوالفقاري\/عليرضا به سپرده700831655066 صندوق سرمايه گذاري امين آشنا ايرانيان حميدرضا ذوالفقاري 0520880706",
  "تاریخ": "1403\/02\/01",
  "زمان": "07:46:48",
  "واریز": 2170000000,
  "برداشت": 0,
  "موجودی": 2237443146,
  "شعبه عامل": "اراک(297)",
  "شماره سند": 7592982254,
  "نام": "حميدرضا",
  "نام خانوادگی": "ذوالفقاري",
  "نام پدر": "عليرضا",
  "کد ملی": "0520880706",
  "سایر": 0,
  "حساب": 4001003642761,
  "*": "*",
  "*": "*",
  "*": "*",
  "شماره": "82710146",
  "کد تفصیل": 1163913,
  "نام": "حميدرضا",
  "نام خانوادگی": "ذوالفقاري",
  "کد ملی": "0520880706",
  "حساب": 506300887800,
  "نوع": "صدور",
  "مبلغ": 2170000000,
  "تاریخ درخواست": "1403\/02\/01",
  "زمان": "07:52",
  "شماره فیش": 101211589,
  " شماره شبا": "IR700150000000506300887803"
 },
 {
  "شرح": "انتقال وجه از سپرده 4001003499672قرض الحسنه جاري بدون دسته چک ليلا\/اذاني\/مسلم به سپرده700831655066 صندوق سرمايه گذاري امين آشنا ايرانيان ليلا اذاني 0602980453 بانک شهر ساوه",
  "تاریخ": "1403\/02\/01",
  "زمان": "13:58:27",
  "واریز": 2153500000,
  "برداشت": 0,
  "موجودی": 105284263146,
  "شعبه عامل": "ساوه (استان مرکزی)(430)",
  "شماره سند": 7594474337,
  "نام": "ليلا",
  "نام خانوادگی": "اذاني",
  "نام پدر": "مسلم",
  "کد ملی": "0602980453",
  "سایر": 0,
  "حساب": 4001003499672,
  "*": "*",
  "*": "*",
  "*": "*",
  "شماره": "82721022",
  "کد تفصیل": 1163256,
  "نام": "ليلا",
  "نام خانوادگی": "اذاني",
  "کد ملی": "0602980453",
  "حساب": 4001003499672,
  "نوع": "صدور",
  "مبلغ": 2153500000,
  "تاریخ درخواست": "1403\/02\/01",
  "زمان": "13:53",
  "شماره فیش": 95414993,
  " شماره شبا": "IR210610000004001003499672"
 },
 {
  "شرح": "انتقال وجه از سپرده 4001003647390سپرده قرض الحسنه پس انداز (حقيقي) اکرم\/داودآبادي\/محمد به سپرده700831655066 صندوق سرمايه گذاري امين آشنا ايرانيان ",
  "تاریخ": "1403\/02\/01",
  "زمان": "14:57:53",
  "واریز": 2073000000,
  "برداشت": 0,
  "موجودی": 15282363146,
  "شعبه عامل": "اراک(297)",
  "شماره سند": 7594708145,
  "نام": "اکرم",
  "نام خانوادگی": "داودآبادي",
  "نام پدر": "محمد",
  "کد ملی": 0,
  "سایر": 0,
  "حساب": 4001003647390,
  "*": "*",
  "*": "*",
  "*": "*",
  "شماره": "82721843",
  "کد تفصیل": 1163942,
  "نام": "اكرم",
  "نام خانوادگی": "داودآبادي",
  "کد ملی": "0531008436",
  "حساب": 4001003647390,
  "نوع": "صدور",
  "مبلغ": 2073000000,
  "تاریخ درخواست": "1403\/02\/01",
  "زمان": "14:58",
  "شماره فیش": 100131929,
  " شماره شبا": "IR810610000004001003647390"
 },
 {
  "شرح": "انتقال وجه از سپرده 700822210202سپرده سرمايه گذاري عادي حامد\/رحماني\/علي به سپرده700831655066 صندوق سرمايه گذاري امين آشنا ايرانيان حامد رحماني 4592116410سند 99958238",
  "تاریخ": "1403\/02\/01",
  "زمان": "14:25:03",
  "واریز": 2000000000,
  "برداشت": 0,
  "موجودی": 137109763146,
  "شعبه عامل": "شاهرود(2882)",
  "شماره سند": 7594586097,
  "نام": "حامد",
  "نام خانوادگی": "رحماني",
  "نام پدر": "علي",
  "کد ملی": "4592116410",
  "سایر": "99958238",
  "حساب": 700822210202,
  "*": "*",
  "*": "*",
  "*": "*",
  "شماره": "82721428",
  "کد تفصیل": 1159050,
  "نام": "حامد",
  "نام خانوادگی": "رحماني",
  "کد ملی": "4592116410",
  "حساب": 337761117004,
  "نوع": "صدور",
  "مبلغ": 2000000000,
  "تاریخ درخواست": "1403\/02\/01",
  "زمان": "14:28",
  "شماره فیش": 99958238,
  " شماره شبا": "IR320170000000337761117004"
 },
 {
  "شرح": "انتقال وجه از سپرده 700800860952سپرده سرمايه گذاري عادي مرتضي\/خورسندي\/محمد به سپرده700831655066 صندوق سرمايه گذاري امين آشنا ايرانيان 1110501978",
  "تاریخ": "1403\/02\/01",
  "زمان": "10:42:17",
  "واریز": 2000000000,
  "برداشت": 0,
  "موجودی": 35585443146,
  "شعبه عامل": "چهارراه نورباران(303)",
  "شماره سند": 7593572385,
  "نام": "مرتضي",
  "نام خانوادگی": "خورسندي",
  "نام پدر": "محمد",
  "کد ملی": "1110501978",
  "سایر": 0,
  "حساب": 700800860952,
  "*": "*",
  "*": "*",
  "*": "*",
  "شماره": "82713405",
  "کد تفصیل": 1159173,
  "نام": "مرتضي",
  "نام خانوادگی": "خورسندي",
  "کد ملی": "1110501978",
  "حساب": 700800860952,
  "نوع": "صدور",
  "مبلغ": 2000000000,
  "تاریخ درخواست": "1403\/02\/01",
  "زمان": "10:43",
  "شماره فیش": 4645058,
  " شماره شبا": "IR300610000000700800860952"
 },
 {
  "شرح": "انتقال وجه از سپرده 7001003601974سپرده سرمايه گذاري عادي سيده فاطمه\/حسيني\/سيدکاظم به سپرده700831655066 صندوق سرمايه گذاري امين آشنا ايرانيان سيده فاطمه حسيني0602401933",
  "تاریخ": "1403\/02\/01",
  "زمان": "16:21:34",
  "واریز": 1959500000,
  "برداشت": 0,
  "موجودی": 1972573146,
  "شعبه عامل": "ساوه (استان مرکزی)(430)",
  "شماره سند": 7594958942,
  "نام": "سيده فاطمه",
  "نام خانوادگی": "حسيني",
  "نام پدر": "سيدکاظم",
  "کد ملی": "0602401933",
  "سایر": 0,
  "حساب": 7001003601974,
  "*": "*",
  "*": "*",
  "*": "*",
  "شماره": "82725586",
  "کد تفصیل": 1163340,
  "نام": "سيده فاطمه",
  "نام خانوادگی": "حسيني",
  "کد ملی": "0602401933",
  "حساب": 1003601974,
  "نوع": "صدور",
  "مبلغ": 1959500000,
  "تاریخ درخواست": "1403\/02\/01",
  "زمان": "16:18",
  "شماره فیش": 97959502,
  " شماره شبا": "IR630610000007001003601974"
 },
 {
  "شرح": "انتقال وجه از سپرده 4001003383627قرض الحسنه جاري بدون دسته چک اعظم\/کمالي طراقي\/حسين به سپرده700831655066 صندوق سرمايه گذاري امين آشنا ايرانيان 0682090077 اعظم کمالي طراقي",
  "تاریخ": "1403\/02\/01",
  "زمان": "10:52:15",
  "واریز": 1600000000,
  "برداشت": 0,
  "موجودی": 37185443146,
  "شعبه عامل": "هاشمیه(447)",
  "شماره سند": 7593615052,
  "نام": "اعظم",
  "نام خانوادگی": "کمالي طراقي",
  "نام پدر": "حسين",
  "کد ملی": "0682090077",
  "سایر": 0,
  "حساب": 4001003383627,
  "*": "*",
  "*": "*",
  "*": "*",
  "شماره": "82713503",
  "کد تفصیل": 1158837,
  "نام": "اعظم",
  "نام خانوادگی": "كمالي طراقي",
  "کد ملی": "0682090077",
  "حساب": 112776863003,
  "نوع": "صدور",
  "مبلغ": 1600000000,
  "تاریخ درخواست": "1403\/02\/01",
  "زمان": "10:52",
  "شماره فیش": 103079454,
  " شماره شبا": "IR300190000000112776863003"
 },
 {
  "شرح": "انتقال وجه از سپرده 4001003597998قرض الحسنه جاري بدون دسته چک اشکان\/بابائي\/احمد به سپرده700831655066 صندوق سرمايه گذاري امين آشنا ايرانيان 101605074",
  "تاریخ": "1403\/02\/01",
  "زمان": "15:03:25",
  "واریز": 1500000000,
  "برداشت": 0,
  "موجودی": 19033353146,
  "شعبه عامل": "قایم شهر(2792)",
  "شماره سند": 7594725225,
  "نام": "اشکان",
  "نام خانوادگی": "بابائي",
  "نام پدر": "احمد",
  "کد ملی": 0,
  "سایر": "101605074",
  "حساب": 4001003597998,
  "*": "*",
  "*": "*",
  "*": "*",
  "شماره": "82722756",
  "کد تفصیل": 1163437,
  "نام": "اشكان",
  "نام خانوادگی": "بابائي",
  "کد ملی": "2150701049",
  "حساب": 4001003597998,
  "نوع": "صدور",
  "مبلغ": 1500000000,
  "تاریخ درخواست": "1403\/02\/01",
  "زمان": "15:13",
  "شماره فیش": 101605074,
  " شماره شبا": "IR120610000004001003597998"
 },
 {
  "شرح": "انتقال وجه از سپرده 4001003603099قرض الحسنه جاري بدون دسته چک محمود\/محمدپورکله سري\/محمد به سپرده700831655066 صندوق سرمايه گذاري امين آشنا ايرانيان ",
  "تاریخ": "1403\/02\/01",
  "زمان": "15:00:47",
  "واریز": 1250000000,
  "برداشت": 0,
  "موجودی": 17533353146,
  "شعبه عامل": "قایم شهر(2792)",
  "شماره سند": 7594717271,
  "نام": "محمود",
  "نام خانوادگی": "محمدپورکله سري",
  "نام پدر": "محمد",
  "کد ملی": 0,
  "سایر": 0,
  "حساب": 4001003603099,
  "*": "*",
  "*": "*",
  "*": "*",
  "شماره": "82722785",
  "کد تفصیل": 1163920,
  "نام": "محمود",
  "نام خانوادگی": "محمدپور كله سري",
  "کد ملی": "2649177292",
  "حساب": 1003603099,
  "نوع": "صدور",
  "مبلغ": 1250000000,
  "تاریخ درخواست": "1403\/02\/01",
  "زمان": "15:14",
  "شماره فیش": 101605043,
  " شماره شبا": "IR250610000004001003603099"
 },
 {
  "شرح": "انتقال وجه از سپرده 100838636065سپرده قرض الحسنه جاري (بدون دسته چک) طيبه\/کارچاني\/امير به سپرده700831655066 صندوق سرمايه گذاري امين آشنا ايرانيان 0531297861 طيبه کارچاني",
  "تاریخ": "1403\/02\/01",
  "زمان": "08:09:24",
  "واریز": 1200000000,
  "برداشت": 0,
  "موجودی": 9342443146,
  "شعبه عامل": "اراک(297)",
  "شماره سند": 7593045560,
  "نام": "طيبه",
  "نام خانوادگی": "کارچاني",
  "نام پدر": "امير",
  "کد ملی": "0531297861",
  "سایر": 0,
  "حساب": 100838636065,
  "*": "*",
  "*": "*",
  "*": "*",
  "شماره": "82710376",
  "کد تفصیل": 1163915,
  "نام": "طيبه",
  "نام خانوادگی": "كارچاني",
  "کد ملی": "0531297861",
  "حساب": 100838636065,
  "نوع": "صدور",
  "مبلغ": 1200000000,
  "تاریخ درخواست": "1403\/02\/01",
  "زمان": "08:09",
  "شماره فیش": 98610142,
  " شماره شبا": "IR470610000000100838636065"
 },
 {
  "شرح": "انتقال وجه از سپرده 4001001108227قرض الحسنه جاري بدون دسته چک سيدمرتضي\/زارع مؤيدي\/سيداحمد به سپرده700831655066 صندوق سرمايه گذاري امين آشنا ايرانيان سيد مرتضي زارع مويدي2298461465",
  "تاریخ": "1403\/02\/01",
  "زمان": "13:27:36",
  "واریز": 1100000000,
  "برداشت": 0,
  "موجودی": 13868763146,
  "شعبه عامل": "پایانه کاراندیش شیراز(315)",
  "شماره سند": 7594348298,
  "نام": "سيدمرتضي",
  "نام خانوادگی": "زارع مؤيدي",
  "نام پدر": "سيداحمد",
  "کد ملی": "2298461465",
  "سایر": 0,
  "حساب": 4001001108227,
  "*": "*",
  "*": "*",
  "*": "*",
  "شماره": "82719752",
  "کد تفصیل": 1163948,
  "نام": "سيدمرتضي",
  "نام خانوادگی": "زارع مؤيدي",
  "کد ملی": "2298461465",
  "حساب": 356390514004,
  "نوع": "صدور",
  "مبلغ": 1100000000,
  "تاریخ درخواست": "1403\/02\/01",
  "زمان": "13:24",
  "شماره فیش": 76836,
  " شماره شبا": "IR220550230470106283729001"
 },
 {
  "شرح": "انتقال وجه از سپرده 7001003638029سپرده سرمايه گذاري عادي ابوالفضل\/نوازني\/مسيب به سپرده700831655066 صندوق سرمايه گذاري امين آشنا ايرانيان ابوالفضل نوازني 0531804658",
  "تاریخ": "1403\/02\/01",
  "زمان": "15:00:08",
  "واریز": 1000990000,
  "برداشت": 0,
  "موجودی": 16283353146,
  "شعبه عامل": "دکترحسابی(2974)",
  "شماره سند": 7594715291,
  "نام": "ابوالفضل",
  "نام خانوادگی": "نوازني",
  "نام پدر": "مسيب",
  "کد ملی": "0531804658",
  "سایر": 0,
  "حساب": 7001003638029,
  "*": "*",
  "*": "*",
  "*": "*",
  "شماره": "82721854",
  "کد تفصیل": 1163788,
  "نام": "ابوالفضل ",
  "نام خانوادگی": "نوازني",
  "کد ملی": "0531804658",
  "حساب": 7001003638029,
  "نوع": "صدور",
  "مبلغ": 1000990000,
  "تاریخ درخواست": "1403\/02\/01",
  "زمان": "14:59",
  "شماره فیش": 99897585,
  " شماره شبا": "IR700610000007001003638029"
 },
 {
  "شرح": "انتقال وجه از سپرده 4001003647652سپرده قرض الحسنه پس انداز (حقيقي) مصطفي\/کازروني\/عبدالکريم به سپرده700831655066 صندوق سرمايه گذاري امين آشنا ايرانيان 1899608680مصطفي کازروني",
  "تاریخ": "1403\/02\/01",
  "زمان": "14:56:37",
  "واریز": 1000000000,
  "برداشت": 0,
  "موجودی": 145709363146,
  "شعبه عامل": "اراک(297)",
  "شماره سند": 7594704102,
  "نام": "مصطفي",
  "نام خانوادگی": "کازروني",
  "نام پدر": "عبدالکريم",
  "کد ملی": "1899608680",
  "سایر": 0,
  "حساب": 4001003647652,
  "*": "*",
  "*": "*",
  "*": "*",
  "شماره": "82721833",
  "کد تفصیل": 1163960,
  "نام": "مصطفي",
  "نام خانوادگی": "كازروني",
  "کد ملی": "1899608680",
  "حساب": 308597778006,
  "نوع": "صدور",
  "مبلغ": 1000000000,
  "تاریخ درخواست": "1403\/02\/01",
  "زمان": "14:57",
  "شماره فیش": 101643445,
  " شماره شبا": "IR590190000000308597778006"
 },
 {
  "شرح": "انتقال وجه از سپرده 4001003646654قرض الحسنه جاري بدون دسته چک زهرا\/مشهدي\/محمدرضا به سپرده700831655066 صندوق سرمايه گذاري امين آشنا ايرانيان 0621811408",
  "تاریخ": "1403\/02\/01",
  "زمان": "11:25:39",
  "واریز": 1000000000,
  "برداشت": 0,
  "موجودی": 129798943146,
  "شعبه عامل": "اراک(297)",
  "شماره سند": 7593761692,
  "نام": "زهرا",
  "نام خانوادگی": "مشهدي",
  "نام پدر": "محمدرضا",
  "کد ملی": "0621811408",
  "سایر": 0,
  "حساب": 4001003646654,
  "*": "*",
  "*": "*",
  "*": "*",
  "شماره": "82714094",
  "کد تفصیل": 1163933,
  "نام": "زهرا ",
  "نام خانوادگی": "مشهدي ",
  "کد ملی": "0621811408",
  "حساب": 8736732731,
  "نوع": "صدور",
  "مبلغ": 1000000000,
  "تاریخ درخواست": "1403\/02\/01",
  "زمان": "11:26",
  "شماره فیش": 100131275,
  " شماره شبا": "IR310120010000008736732731"
 },
 {
  "شرح": "انتقال وجه از سپرده 4001001615427قرض الحسنه جاري بدون دسته چک الهه\/خوشقولي\/علي اصغر به سپرده700831655066 صندوق سرمايه گذاري امين آشنا ايرانيان الهه خوشقولي 0938783939",
  "تاریخ": "1403\/02\/01",
  "زمان": "07:56:23",
  "واریز": 1000000000,
  "برداشت": 0,
  "موجودی": 3742443146,
  "شعبه عامل": "هاشمیه(447)",
  "شماره سند": 7593008441,
  "نام": "الهه",
  "نام خانوادگی": "خوشقولي",
  "نام پدر": "علي اصغر",
  "کد ملی": "0938783939",
  "سایر": 0,
  "حساب": 4001001615427,
  "*": "*",
  "*": "*",
  "*": "*",
  "شماره": "82710214",
  "کد تفصیل": 1163705,
  "نام": "الهه",
  "نام خانوادگی": "خوشقولي",
  "کد ملی": "0938783939",
  "حساب": 4001001615427,
  "نوع": "صدور",
  "مبلغ": 1000000000,
  "تاریخ درخواست": "1403\/02\/01",
  "زمان": "07:57",
  "شماره فیش": 88306661,
  " شماره شبا": "IR760610000004001001615427"
 },
 {
  "شرح": "انتقال وجه اينترنتي از سپرده 700824613734 به سپرده 700831655066 ",
  "تاریخ": "1403\/02\/01",
  "زمان": "08:12:11",
  "واریز": 800000000,
  "برداشت": 0,
  "موجودی": 10142443146,
  "شعبه عامل": "واحد بانکداری مدرن(116)",
  "شماره سند": 7593053479,
  "نام": "ONLINE",
  "نام خانوادگی": "ONLINE",
  "نام پدر": "ONLINE",
  "کد ملی": "ONLINE",
  "سایر": "ONLINE",
  "حساب": 700824613734,
  "*": "*",
  "*": "*",
  "*": "*",
  "شماره": "w_2943784",
  "کد تفصیل": 1031829,
  "نام": "غلامرضا",
  "نام خانوادگی": "طاوسي",
  "کد ملی": "0016080408",
  "حساب": 700824613734,
  "نوع": "صدور",
  "مبلغ": 800000000,
  "تاریخ درخواست": "1403\/02\/01",
  "زمان": "08:15",
  "شماره فیش": 3020199490416,
  " شماره شبا": "IR190610000000700824613734"
 },
 {
  "شرح": "انتقال وجه از سپرده 700789661207کلانشهرها طاهره\/امينيان\/احمد به سپرده700831655066 صندوق سرمايه گذاري امين آشنا ايرانيان طاهره امينيان 0938588958",
  "تاریخ": "1403\/02\/01",
  "زمان": "07:49:08",
  "واریز": 505000000,
  "برداشت": 0,
  "موجودی": 2742443146,
  "شعبه عامل": "بلوار امامت(541)",
  "شماره سند": 7592988529,
  "نام": "طاهره",
  "نام خانوادگی": "امينيان",
  "نام پدر": "احمد",
  "کد ملی": "0938588958",
  "سایر": 0,
  "حساب": 700789661207,
  "*": "*",
  "*": "*",
  "*": "*",
  "شماره": "82710092",
  "کد تفصیل": 1160424,
  "نام": "طاهره",
  "نام خانوادگی": "امينيان",
  "کد ملی": "0938588958",
  "حساب": 700789661207,
  "نوع": "صدور",
  "مبلغ": 505000000,
  "تاریخ درخواست": "1403\/02\/01",
  "زمان": "07:45",
  "شماره فیش": 556798,
  " شماره شبا": "IR100610000000700789661207"
 },
 {
  "شرح": "انتقال وجه از سپرده 100846874823سپرده قرض الحسنه جاري (بدون دسته چک) مريم\/فياض پور\/علي به سپرده700831655066 صندوق سرمايه گذاري امين آشنا ايرانيان مريم فياض پور 5309478744 سند 99958237",
  "تاریخ": "1403\/02\/01",
  "زمان": "14:21:23",
  "واریز": 500000000,
  "برداشت": 0,
  "موجودی": 135109763146,
  "شعبه عامل": "شاهرود(2882)",
  "شماره سند": 7594573173,
  "نام": "مريم",
  "نام خانوادگی": "فياض پور",
  "نام پدر": "علي",
  "کد ملی": "5309478744",
  "سایر": "99958237",
  "حساب": 100846874823,
  "*": "*",
  "*": "*",
  "*": "*",
  "شماره": "82721337",
  "کد تفصیل": 1160033,
  "نام": "مريم",
  "نام خانوادگی": "فياض پور",
  "کد ملی": "5309478744",
  "حساب": 100846874823,
  "نوع": "صدور",
  "مبلغ": 500000000,
  "تاریخ درخواست": "1403\/02\/01",
  "زمان": "14:23",
  "شماره فیش": 99958237,
  " شماره شبا": "IR920610000000100846874823"
 },
 {
  "شرح": "انتقال وجه از سپرده 700826740683سپرده سرمايه گذاري عادي مرضيه\/شوريابي\/علي اصغر به سپرده700831655066 صندوق سرمايه گذاري امين آشنا ايرانيان 0791182967 مرضيه شوريابي",
  "تاریخ": "1403\/02\/01",
  "زمان": "11:34:20",
  "واریز": 500000000,
  "برداشت": 0,
  "موجودی": 130298943146,
  "شعبه عامل": "هاشمیه(447)",
  "شماره سند": 7593800408,
  "نام": "مرضيه",
  "نام خانوادگی": "شوريابي",
  "نام پدر": "علي اصغر",
  "کد ملی": "0791182967",
  "سایر": 0,
  "حساب": 700826740683,
  "*": "*",
  "*": "*",
  "*": "*",
  "شماره": "82714279",
  "کد تفصیل": 1160175,
  "نام": "مرضيه ",
  "نام خانوادگی": "شوريابي ",
  "کد ملی": "0791182967",
  "حساب": 700826740683,
  "نوع": "صدور",
  "مبلغ": 500000000,
  "تاریخ درخواست": "1403\/02\/01",
  "زمان": "11:35",
  "شماره فیش": 88306679,
  " شماره شبا": "IR820610000000700826740683"
 },
 {
  "شرح": "انتقال وجه اينترنتي از سپرده 700795925505 به سپرده 700831655066 ",
  "تاریخ": "1403\/02\/01",
  "زمان": "10:55:29",
  "واریز": 450000000,
  "برداشت": 0,
  "موجودی": 37635443146,
  "شعبه عامل": "واحد بانکداری مدرن(116)",
  "شماره سند": 7593629148,
  "نام": "ONLINE",
  "نام خانوادگی": "ONLINE",
  "نام پدر": "ONLINE",
  "کد ملی": "ONLINE",
  "سایر": "ONLINE",
  "حساب": 700795925505,
  "*": "*",
  "*": "*",
  "*": "*",
  "شماره": "w_2944406",
  "کد تفصیل": 1018584,
  "نام": "عليرضا",
  "نام خانوادگی": "شهسواري",
  "کد ملی": "0040232727",
  "حساب": 3707515146,
  "نوع": "صدور",
  "مبلغ": 450000000,
  "تاریخ درخواست": "1403\/02\/01",
  "زمان": "10:58",
  "شماره فیش": 3020154596,
  " شماره شبا": "IR340180000000003707515146"
 },
 {
  "شرح": "انتقال وجه از سپرده 4001003611367قرض الحسنه جاري بدون دسته چک طاهره\/زاهديان\/امير به سپرده700831655066 صندوق سرمايه گذاري امين آشنا ايرانيان طاهره زاهديان2301566579",
  "تاریخ": "1403\/02\/01",
  "زمان": "13:20:16",
  "واریز": 440000000,
  "برداشت": 0,
  "موجودی": 12768763146,
  "شعبه عامل": "پایانه کاراندیش شیراز(315)",
  "شماره سند": 7594316643,
  "نام": "طاهره",
  "نام خانوادگی": "زاهديان",
  "نام پدر": "امير",
  "کد ملی": "2301566579",
  "سایر": 0,
  "حساب": 4001003611367,
  "*": "*",
  "*": "*",
  "*": "*",
  "شماره": "82717995",
  "کد تفصیل": 1163946,
  "نام": "طاهره",
  "نام خانوادگی": "زاهديان",
  "کد ملی": "2301566579",
  "حساب": 1003611367,
  "نوع": "صدور",
  "مبلغ": 440000000,
  "تاریخ درخواست": "1403\/02\/01",
  "زمان": "13:10",
  "شماره فیش": 96041947,
  " شماره شبا": "IR830610000004001003611367"
 },
 {
  "شرح": "انتقال وجه از سپرده 700809310439سپرده سرمايه گذاري عادي عباس\/جعفري\/اکرمعلي به سپرده700831655066 صندوق سرمايه گذاري امين آشنا ايرانيان عباس جعفري0603392059 بانک شهر ساوه",
  "تاریخ": "1403\/02\/01",
  "زمان": "09:39:46",
  "واریز": 420000000,
  "برداشت": 0,
  "موجودی": 15870443146,
  "شعبه عامل": "ساوه (استان مرکزی)(430)",
  "شماره سند": 7593332540,
  "نام": "عباس",
  "نام خانوادگی": "جعفري",
  "نام پدر": "اکرمعلي",
  "کد ملی": "0603392059",
  "سایر": 0,
  "حساب": 700809310439,
  "*": "*",
  "*": "*",
  "*": "*",
  "شماره": "82711419",
  "کد تفصیل": 1161264,
  "نام": "عباس",
  "نام خانوادگی": "جعفري",
  "کد ملی": "0603392059",
  "حساب": 700809310439,
  "نوع": "صدور",
  "مبلغ": 420000000,
  "تاریخ درخواست": "1403\/02\/01",
  "زمان": "09:01",
  "شماره فیش": 95414987,
  " شماره شبا": "IR240610000000700809310439"
 },
 {
  "شرح": "انتقال وجه از سپرده 700791861449سپرده کوتاه مدت آرزو\/مهرآور\/اختيار به سپرده700831655066 صندوق سرمايه گذاري امين آشنا ايرانيان ",
  "تاریخ": "1403\/02\/01",
  "زمان": "08:58:31",
  "واریز": 400000000,
  "برداشت": 0,
  "موجودی": 10542443146,
  "شعبه عامل": "خسروی نو(374)",
  "شماره سند": 7593191982,
  "نام": "آرزو",
  "نام خانوادگی": "مهرآور",
  "نام پدر": "اختيار",
  "کد ملی": 0,
  "سایر": 0,
  "حساب": 700791861449,
  "*": "*",
  "*": "*",
  "*": "*",
  "شماره": "82711391",
  "کد تفصیل": 1159158,
  "نام": "آرزو",
  "نام خانوادگی": "مهرآور",
  "کد ملی": "0075574871",
  "حساب": 700791861449,
  "نوع": "صدور",
  "مبلغ": 400000000,
  "تاریخ درخواست": "1403\/02\/01",
  "زمان": "08:59",
  "شماره فیش": 103265390,
  " شماره شبا": "IR590610000000700791861449"
 },
 {
  "شرح": "انتقال وجه از سپرده 700791869970سپرده سرمايه گذاري کوتاه مدت - مهدي\/الياسي\/عبداله به سپرده700831655066 صندوق سرمايه گذاري امين آشنا ايرانيان مهدي الياسي0603255809 بانک شهر ساوه",
  "تاریخ": "1403\/02\/01",
  "زمان": "13:51:13",
  "واریز": 312000000,
  "برداشت": 0,
  "موجودی": 14380763146,
  "شعبه عامل": "ساوه (استان مرکزی)(430)",
  "شماره سند": 7594445032,
  "نام": "- مهدي",
  "نام خانوادگی": "الياسي",
  "نام پدر": "عبداله",
  "کد ملی": "0603255809",
  "سایر": 0,
  "حساب": 700791869970,
  "*": "*",
  "*": "*",
  "*": "*",
  "شماره": "82718850",
  "کد تفصیل": 1160652,
  "نام": "مهدي",
  "نام خانوادگی": "الياسي",
  "کد ملی": "0603255809",
  "حساب": 700791869970,
  "نوع": "صدور",
  "مبلغ": 312000000,
  "تاریخ درخواست": "1403\/02\/01",
  "زمان": "13:16",
  "شماره فیش": 97084684,
  " شماره شبا": "IR760610000000700791869970"
 },
 {
  "شرح": "انتقال وجه اينترنتي از سپرده 700799879096 به سپرده 700831655066 ",
  "تاریخ": "1403\/02\/01",
  "زمان": "11:24:12",
  "واریز": 284500000,
  "برداشت": 0,
  "موجودی": 78548943146,
  "شعبه عامل": "واحد بانکداری مدرن(116)",
  "شماره سند": 7593755306,
  "نام": "ONLINE",
  "نام خانوادگی": "ONLINE",
  "نام پدر": "ONLINE",
  "کد ملی": "ONLINE",
  "سایر": "ONLINE",
  "حساب": 700799879096,
  "*": "*",
  "*": "*",
  "*": "*",
  "شماره": "w_2944500",
  "کد تفصیل": 1042416,
  "نام": "عبد المجيد",
  "نام خانوادگی": "سبحاني ثابت",
  "کد ملی": "0381300633",
  "حساب": 700799879096,
  "نوع": "صدور",
  "مبلغ": 284500000,
  "تاریخ درخواست": "1403\/02\/01",
  "زمان": "11:30",
  "شماره فیش": 30201178097,
  " شماره شبا": "IR420610000000700799879096"
 },
 {
  "شرح": "انتقال وجه از سپرده 700796899345کوتاه مدت رامين دهقان\/محمد رضا به سپرده700831655066 صندوق سرمايه گذاري امين آشنا ايرانيان رامين دهقان2281558134",
  "تاریخ": "1403\/02\/01",
  "زمان": "13:53:23",
  "واریز": 250000000,
  "برداشت": 0,
  "موجودی": 14630763146,
  "شعبه عامل": "پایانه کاراندیش شیراز(315)",
  "شماره سند": 7594453400,
  "نام": "رامين دهقان",
  "نام خانوادگی": "محمد رضا",
  "نام پدر": "BLANK",
  "کد ملی": "2281558134",
  "سایر": 0,
  "حساب": 700796899345,
  "*": "*",
  "*": "*",
  "*": "*",
  "شماره": "82720992",
  "کد تفصیل": 1163725,
  "نام": "رامين",
  "نام خانوادگی": "دهقان",
  "کد ملی": "2281558134",
  "حساب": 700796899345,
  "نوع": "صدور",
  "مبلغ": 250000000,
  "تاریخ درخواست": "1403\/02\/01",
  "زمان": "13:51",
  "شماره فیش": 76835,
  " شماره شبا": "IR640610000000700796899345"
 },
 {
  "شرح": "انتقال وجه از سپرده 7007283370سرمايه گذاري کوتاه مدت عادي محمدمهدي\/اسماعيليابهري\/يداله به سپرده700831655066 صندوق سرمايه گذاري امين آشنا ايرانيان 2571677292",
  "تاریخ": "1403\/02\/01",
  "زمان": "12:22:29",
  "واریز": 250000000,
  "برداشت": 0,
  "موجودی": 130707043146,
  "شعبه عامل": "بلوار ازادی شیراز(383)",
  "شماره سند": 7594026837,
  "نام": "محمدمهدي",
  "نام خانوادگی": "اسماعيليابهري",
  "نام پدر": "يداله",
  "کد ملی": "2571677292",
  "سایر": 0,
  "حساب": 7007283370,
  "*": "*",
  "*": "*",
  "*": "*",
  "شماره": "82716417",
  "کد تفصیل": 1161570,
  "نام": "محمدمهدي",
  "نام خانوادگی": "اسمعيلي ابهري",
  "کد ملی": "2571677292",
  "حساب": 7007283370,
  "نوع": "صدور",
  "مبلغ": 250000000,
  "تاریخ درخواست": "1403\/02\/01",
  "زمان": "12:22",
  "شماره فیش": 95888020,
  " شماره شبا": "IR790610000000007007283370"
 },
 {
  "شرح": "انتقال وجه از سپرده 700840823416سپرده سرمايه گذاري عادي دانيال\/کاشفي\/محمدهادي به سپرده700831655066 صندوق سرمايه گذاري امين آشنا ايرانيان 0921535805 دانيال کاشفي",
  "تاریخ": "1403\/02\/01",
  "زمان": "13:38:44",
  "واریز": 200000000,
  "برداشت": 0,
  "موجودی": 14068763146,
  "شعبه عامل": "هاشمیه(447)",
  "شماره سند": 7594394862,
  "نام": "دانيال",
  "نام خانوادگی": "کاشفي",
  "نام پدر": "محمدهادي",
  "کد ملی": "0921535805",
  "سایر": 0,
  "حساب": 700840823416,
  "*": "*",
  "*": "*",
  "*": "*",
  "شماره": "82720791",
  "کد تفصیل": 1160399,
  "نام": "دانيال ",
  "نام خانوادگی": "كاشفي ",
  "کد ملی": "0921535805",
  "حساب": 700840823416,
  "نوع": "صدور",
  "مبلغ": 200000000,
  "تاریخ درخواست": "1403\/02\/01",
  "زمان": "13:40",
  "شماره فیش": 93895,
  " شماره شبا": "IR830610000000700840823416"
 },
 {
  "شرح": "انتقال وجه از سپرده 700824253226سپرده سرمايه گذاري عادي محمدرضا\/هدايتي اصل\/اسداله به سپرده700831655066 صندوق سرمايه گذاري امين آشنا ايرانيان محمد رضا هدايتي 0652438563شعبه بيرجند کد306",
  "تاریخ": "1403\/02\/01",
  "زمان": "14:39:25",
  "واریز": 173000000,
  "برداشت": 0,
  "موجودی": 144709363146,
  "شعبه عامل": "بیرجند(306)",
  "شماره سند": 7594648743,
  "نام": "محمدرضا",
  "نام خانوادگی": "هدايتي اصل",
  "نام پدر": "اسداله",
  "کد ملی": "0652438563",
  "سایر": "306",
  "حساب": 700824253226,
  "*": "*",
  "*": "*",
  "*": "*",
  "شماره": "82721646",
  "کد تفصیل": 1159456,
  "نام": "محمدرضا",
  "نام خانوادگی": "هدايتي اصل",
  "کد ملی": "0652438563",
  "حساب": 700824253226,
  "نوع": "صدور",
  "مبلغ": 173000000,
  "تاریخ درخواست": "1403\/02\/01",
  "زمان": "14:43",
  "شماره فیش": 77122688,
  " شماره شبا": "IR760610000000700824253226"
 },
 {
  "شرح": "انتقال وجه از سپرده 700811269177سپرده سرمايه گذاري عادي حسن\/يارمحمدي\/نادعلي به سپرده700831655066 صندوق سرمايه گذاري امين آشنا ايرانيان 0451628748",
  "تاریخ": "1403\/02\/01",
  "زمان": "12:00:52",
  "واریز": 131000000,
  "برداشت": 0,
  "موجودی": 130457043146,
  "شعبه عامل": "میدان هروی(490)",
  "شماره سند": 7593922346,
  "نام": "حسن",
  "نام خانوادگی": "يارمحمدي",
  "نام پدر": "نادعلي",
  "کد ملی": "0451628748",
  "سایر": 0,
  "حساب": 700811269177,
  "*": "*",
  "*": "*",
  "*": "*",
  "شماره": "w_2944798",
  "کد تفصیل": 1028518,
  "نام": "حسن",
  "نام خانوادگی": "يارمحمدي",
  "کد ملی": "0451628748",
  "حساب": 700811269177,
  "نوع": "صدور",
  "مبلغ": 131000000,
  "تاریخ درخواست": "1403\/02\/01",
  "زمان": "13:13",
  "شماره فیش": 100687295,
  " شماره شبا": "IR500610000000700811269177"
 },
 {
  "شرح": "انتقال وجه از سپرده 7001003449744سپرده سرمايه گذاري عادي غلامحسين\/ده بزرگي\/عباس به سپرده700831655066 صندوق سرمايه گذاري امين آشنا ايرانيان 1818403684",
  "تاریخ": "1403\/02\/01",
  "زمان": "09:11:26",
  "واریز": 120000000,
  "برداشت": 0,
  "موجودی": 15450443146,
  "شعبه عامل": "بلوار ازادی شیراز(383)",
  "شماره سند": 7593234446,
  "نام": "غلامحسين",
  "نام خانوادگی": "ده بزرگي",
  "نام پدر": "عباس",
  "کد ملی": "1818403684",
  "سایر": 0,
  "حساب": 7001003449744,
  "*": "*",
  "*": "*",
  "*": "*",
  "شماره": "82711711",
  "کد تفصیل": 1160554,
  "نام": "غلامحسين",
  "نام خانوادگی": "ده بزرگي",
  "کد ملی": "1818403684",
  "حساب": 1003449744,
  "نوع": "صدور",
  "مبلغ": 120000000,
  "تاریخ درخواست": "1403\/02\/01",
  "زمان": "09:11",
  "شماره فیش": 101029245,
  " شماره شبا": "IR920610000007001003449744"
 },
 {
  "شرح": "انتقال وجه از سپرده 700794964885سپرده سرمايه گذاري عادي فرشته\/کامکار يزد نژاد\/علي به سپرده700831655066 صندوق سرمايه گذاري امين آشنا ايرانيان فرشته کامکار يزد نژاد",
  "تاریخ": "1403\/02\/01",
  "زمان": "12:29:13",
  "واریز": 102000000,
  "برداشت": 0,
  "موجودی": 130809043146,
  "شعبه عامل": "بلوار امامت(541)",
  "شماره سند": 7594060244,
  "نام": "فرشته",
  "نام خانوادگی": "کامکار يزد نژاد",
  "نام پدر": "علي",
  "کد ملی": 0,
  "سایر": 0,
  "حساب": 700794964885,
  "*": "*",
  "*": "*",
  "*": "*",
  "شماره": "82716466",
  "کد تفصیل": 1162189,
  "نام": "فرشته",
  "نام خانوادگی": "كامكار يزد نژاد",
  "کد ملی": "0946599513",
  "حساب": 700794964885,
  "نوع": "صدور",
  "مبلغ": 102000000,
  "تاریخ درخواست": "1403\/02\/01",
  "زمان": "12:26",
  "شماره فیش": 556785,
  " شماره شبا": "IR580610000000700794964885"
 },
 {
  "شرح": "انتقال وجه اينترنتي از سپرده 400814549776 به سپرده 700831655066 ",
  "تاریخ": "1403\/02\/01",
  "زمان": "14:33:15",
  "واریز": 100600000,
  "برداشت": 0,
  "موجودی": 140210363146,
  "شعبه عامل": "واحد بانکداری مدرن(116)",
  "شماره سند": 7594625775,
  "نام": "ONLINE",
  "نام خانوادگی": "ONLINE",
  "نام پدر": "ONLINE",
  "کد ملی": "ONLINE",
  "سایر": "ONLINE",
  "حساب": 400814549776,
  "*": "*",
  "*": "*",
  "*": "*",
  "شماره": "w_2944981",
  "کد تفصیل": 1012257,
  "نام": "علي",
  "نام خانوادگی": "حدادي",
  "کد ملی": "3610610077",
  "حساب": 1082207221,
  "نوع": "صدور",
  "مبلغ": 100600000,
  "تاریخ درخواست": "1403\/02\/01",
  "زمان": "14:34",
  "شماره فیش": 302011034300,
  " شماره شبا": "IR240700001000118220722001"
 },
 {
  "شرح": "انتقال وجه اينترنتي از سپرده 700815416253 به سپرده 700831655066 ",
  "تاریخ": "1403\/02\/01",
  "زمان": "15:25:20",
  "واریز": 80000000,
  "برداشت": 0,
  "موجودی": 68113353146,
  "شعبه عامل": "واحد بانکداری مدرن(116)",
  "شماره سند": 7594790022,
  "نام": "ONLINE",
  "نام خانوادگی": "ONLINE",
  "نام پدر": "ONLINE",
  "کد ملی": "ONLINE",
  "سایر": "ONLINE",
  "حساب": 700815416253,
  "*": "*",
  "*": "*",
  "*": "*",
  "شماره": "w_2945104",
  "کد تفصیل": 1042307,
  "نام": "زاهد",
  "نام خانوادگی": "رؤفي",
  "کد ملی": "2631502027",
  "حساب": 700815416253,
  "نوع": "صدور",
  "مبلغ": 80000000,
  "تاریخ درخواست": "1403\/02\/01",
  "زمان": "15:29",
  "شماره فیش": 302011196263,
  " شماره شبا": "IR750610000000700815416253"
 },
 {
  "شرح": "انتقال وجه از سپرده 700826470984سپرده سرمايه گذاري عادي سکينه\/دستجاني فراهاني\/اسداله به سپرده700831655066 صندوق سرمايه گذاري امين آشنا ايرانيان ",
  "تاریخ": "1403\/02\/01",
  "زمان": "11:56:21",
  "واریز": 27100000,
  "برداشت": 0,
  "موجودی": 130326043146,
  "شعبه عامل": "اراک(297)",
  "شماره سند": 7593901030,
  "نام": "سکينه",
  "نام خانوادگی": "دستجاني فراهاني",
  "نام پدر": "اسداله",
  "کد ملی": 0,
  "سایر": 0,
  "حساب": 700826470984,
  "*": "*",
  "*": "*",
  "*": "*",
  "شماره": "82715395",
  "کد تفصیل": 1163936,
  "نام": "سكينه",
  "نام خانوادگی": "دستجاني فراهاني",
  "کد ملی": "5449889542",
  "حساب": 8441886076,
  "نوع": "صدور",
  "مبلغ": 27100000,
  "تاریخ درخواست": "1403\/02\/01",
  "زمان": "11:57",
  "شماره فیش": 100131924,
  " شماره شبا": "IR450120020000008441886076"
 },
 {
  "شرح": "انتقال وجه اينترنتي از سپرده 700805461582 به سپرده 700831655066 ",
  "تاریخ": "1403\/02\/01",
  "زمان": "14:01:51",
  "واریز": 20500000,
  "برداشت": 0,
  "موجودی": 123304763146,
  "شعبه عامل": "واحد بانکداری مدرن(116)",
  "شماره سند": 7594488313,
  "نام": "ONLINE",
  "نام خانوادگی": "ONLINE",
  "نام پدر": "ONLINE",
  "کد ملی": "ONLINE",
  "سایر": "ONLINE",
  "حساب": 700805461582,
  "*": "*",
  "*": "*",
  "*": "*",
  "شماره": "w_2944910",
  "کد تفصیل": 1045737,
  "نام": "سينا",
  "نام خانوادگی": "جعفري مرند",
  "کد ملی": "1570190151",
  "حساب": 700805461582,
  "نوع": "صدور",
  "مبلغ": 20500000,
  "تاریخ درخواست": "1403\/02\/01",
  "زمان": "14:04",
  "شماره فیش": 30201898126,
  " شماره شبا": "IR560610000000700805461582"
 },
 {
  "شرح": "انتقال وجه از سپرده 700835926810سپرده سرمايه گذاري عادي معصومه\/قربان خاني\/قربان به سپرده700831655066 صندوق سرمايه گذاري امين آشنا ايرانيان  معصومه قرباني خاني0054295637",
  "تاریخ": "1403\/02\/01",
  "زمان": "12:54:56",
  "واریز": 20000000,
  "برداشت": 0,
  "موجودی": 3828763146,
  "شعبه عامل": "اراک(297)",
  "شماره سند": 7594197495,
  "نام": "معصومه",
  "نام خانوادگی": "قربان خاني",
  "نام پدر": "قربان",
  "کد ملی": "0054295637",
  "سایر": 0,
  "حساب": 700835926810,
  "*": "*",
  "*": "*",
  "*": "*",
  "شماره": "82717018",
  "کد تفصیل": 1161123,
  "نام": "معصومه ",
  "نام خانوادگی": "قربان خاني",
  "کد ملی": "0054295637",
  "حساب": 700835926810,
  "نوع": "صدور",
  "مبلغ": 20000000,
  "تاریخ درخواست": "1403\/02\/01",
  "زمان": "12:55",
  "شماره فیش": 98610196,
  " شماره شبا": "IR640610000000700835926810"
 },
 {
  "شرح": "انتقال وجه اينترنتي از سپرده 700805461582 به سپرده 700831655066 ",
  "تاریخ": "1403\/02\/01",
  "زمان": "14:05:15",
  "واریز": 5000000,
  "برداشت": 0,
  "موجودی": 123309763146,
  "شعبه عامل": "واحد بانکداری مدرن(116)",
  "شماره سند": 7594502307,
  "نام": "ONLINE",
  "نام خانوادگی": "ONLINE",
  "نام پدر": "ONLINE",
  "کد ملی": "ONLINE",
  "سایر": "ONLINE",
  "حساب": 700805461582,
  "*": "*",
  "*": "*",
  "*": "*",
  "شماره": "w_2944920",
  "کد تفصیل": 1045737,
  "نام": "سينا",
  "نام خانوادگی": "جعفري مرند",
  "کد ملی": "1570190151",
  "حساب": 700805461582,
  "نوع": "صدور",
  "مبلغ": 5000000,
  "تاریخ درخواست": "1403\/02\/01",
  "زمان": "14:06",
  "شماره فیش": 30201911935,
  " شماره شبا": "IR560610000000700805461582"
 },
 {
  "شرح": "انتقال وجه از سپرده 4001003635195قرض الحسنه جاري بدون دسته چک سميرا\/دهقاني\/کورش به سپرده700831655066 صندوق سرمايه گذاري امين آشنا ايرانيان ",
  "تاریخ": "1403\/02\/01",
  "زمان": "13:01:51",
  "واریز": 2000000000,
  "برداشت": 0,
  "موجودی": 5828763146,
  "شعبه عامل": "بلوار پاسداران(384)",
  "شماره سند": 7594232609,
  "نام": "سميرا",
  "نام خانوادگی": "دهقاني",
  "نام پدر": "کورش",
  "کد ملی": 0,
  "سایر": 0,
  "حساب": 4001003635195,
  "*": "*",
  "*": "*",
  "*": "*",
  "شماره": "82717071",
  "کد تفصیل": 1163945,
  "نام": "سميرا",
  "نام خانوادگی": "دهقاني",
  "کد ملی": "2298463761",
  "حساب": 4001003635195,
  "نوع": "صدور",
  "مبلغ": 2000000000,
  "تاریخ درخواست": "1403\/02\/01",
  "زمان": "12:59",
  "شماره فیش": 95409383,
  " شماره شبا": "IR310610000004001003635195"
 },
 {
  "شرح": "انتقال وجه از سپرده 4001003014721قرض الحسنه جاري بدون دسته چک شهربانو\/ايزانلو\/عوض محمد به سپرده700831655066 صندوق سرمايه گذاري امين آشنا ايرانيان ",
  "تاریخ": "1403\/02\/01",
  "زمان": "12:40:11",
  "واریز": 2000000000,
  "برداشت": 0,
  "موجودی": 3108763146,
  "شعبه عامل": "بجنورد(292)",
  "شماره سند": 7594114900,
  "نام": "شهربانو",
  "نام خانوادگی": "ايزانلو",
  "نام پدر": "عوض محمد",
  "کد ملی": 0,
  "سایر": 0,
  "حساب": 4001003014721,
  "*": "*",
  "*": "*",
  "*": "*",
  "شماره": "82716710",
  "کد تفصیل": 1163941,
  "نام": "شهربانو",
  "نام خانوادگی": "ايزانلو",
  "کد ملی": "0681991496",
  "حساب": 1003014721,
  "نوع": "صدور",
  "مبلغ": 2000000000,
  "تاریخ درخواست": "1403\/02\/01",
  "زمان": "12:41",
  "شماره فیش": 96611331,
  " شماره شبا": "IR560610000004001003014721"
 },
 {
  "شرح": "انتقال وجه از سپرده 7001002391390سپرده سرمايه گذاري عادي رضا\/يزدي\/علي به سپرده700831655066 صندوق سرمايه گذاري امين آشنا ايرانيان رضا يزدي 060118088",
  "تاریخ": "1403\/02\/01",
  "زمان": "11:24:16",
  "واریز": 1000000000,
  "برداشت": 0,
  "موجودی": 79548943146,
  "شعبه عامل": "ساوه (استان مرکزی)(430)",
  "شماره سند": 7593755622,
  "نام": "رضا",
  "نام خانوادگی": "يزدي",
  "نام پدر": "علي",
  "کد ملی": 0,
  "سایر": "060118088",
  "حساب": 7001002391390,
  "*": "*",
  "*": "*",
  "*": "*",
  "شماره": "82712609",
  "کد تفصیل": 1163649,
  "نام": "رضا ",
  "نام خانوادگی": "يزدي",
  "کد ملی": "0600118088",
  "حساب": 710137340505,
  "نوع": "صدور",
  "مبلغ": 1000000000,
  "تاریخ درخواست": "1403\/02\/01",
  "زمان": "09:52",
  "شماره فیش": 97084618,
  " شماره شبا": "IR470140040000710137340505"
 },
 {
  "شرح": "انتقال وجه از سپرده 4001003010563قرض الحسنه جاري بدون دسته چک سودابه\/افشارزاده\/اکبر به سپرده700831655066 صندوق سرمايه گذاري امين آشنا ايرانيان 101605284",
  "تاریخ": "1403\/02\/01",
  "زمان": "14:57:10",
  "واریز": 200000000,
  "برداشت": 0,
  "موجودی": 145909363146,
  "شعبه عامل": "قایم شهر(2792)",
  "شماره سند": 7594705896,
  "نام": "سودابه",
  "نام خانوادگی": "افشارزاده",
  "نام پدر": "اکبر",
  "کد ملی": 0,
  "سایر": "101605284",
  "حساب": 4001003010563,
  "*": "*",
  "*": "*",
  "*": "*",
  "شماره": "82722854",
  "کد تفصیل": 1158371,
  "نام": "سودابه",
  "نام خانوادگی": "افشارزاده",
  "کد ملی": "2162478171",
  "حساب": 4001003010563,
  "نوع": "صدور",
  "مبلغ": 200000000,
  "تاریخ درخواست": "1403\/02\/01",
  "زمان": "15:15",
  "شماره فیش": 101605284,
  " شماره شبا": "IR930610000004001003010563"
 }
],
"Multi Match":[
  "شرح": null,
  "تاریخ": null,
  "زمان": null,
  "واریز": null,
  "برداشت": null,
  "موجودی": null,
  "شعبه عامل": null,
  "شماره سند": null,
  "نام": null,
  "نام خانوادگی": null,
  "نام پدر": null,
  "کد ملی": null,
  "سایر": null,
  "حساب": null,
  "*": null,
  "*": null,
  "*": null,
  "شماره": null,
  "کد تفصیل": null,
  "نام": null,
  "نام خانوادگی": null,
  "کد ملی": null,
  "حساب": null,
  "نوع": null,
  "تعداد": null,
  "مبلغ": null,
  "تاریخ درخواست": null,
  "زمان": null,
  "شماره فیش": null,
  " شماره شبا": null
],
"Non-Matches Ryan":[
 {
  "شماره": "82721315",
  "کد تفصیل": 1163934,
  "نام": "فرشيد",
  "نام خانوادگی": "عزيزي فرد خالص",
  "کد ملی": "2298070611",
  "حساب": 5738046813,
  "نوع": "صدور",
  "مبلغ": 3000000000,
  "تاریخ درخواست": "1403\/02\/01",
  "زمان": "14:21",
  "شماره فیش": 93171709,
  " شماره شبا": "IR170180000000005738046813"
 }
],
"Non-Matches Shahr":[
 {
  "شرح": "انتقال وجه از سپرده 700791256616سپرده کوتاه مدت\/ نوشين تجويدي\/نويد قرباني به سپرده700831655066 صندوق سرمايه گذاري امين آشنا ايرانيان نوشين تجويدي 1755960557",
  "تاریخ": "1403\/02\/01",
  "زمان": "14:57:16",
  "واریز": 12000000000,
  "برداشت": 0,
  "موجودی": 157909363146,
  "شعبه عامل": "دکترحسابی(2974)",
  "شماره سند": 7594706181,
  "نام": "کوتاه مدت",
  "نام خانوادگی": "نوشين تجويدي",
  "نام پدر": "نويد قرباني",
  "کد ملی": "1755960557",
  "سایر": 0,
  "حساب": 700791256616
 },
 {
  "شرح": "انتقال وجه از سپرده 4001003646977قرض الحسنه جاري بدون دسته چک فرشيد\/عزيزي فردخالص\/رمضانعلي به سپرده700831655066 صندوق سرمايه گذاري امين آشنا ايرانيان ",
  "تاریخ": "1403\/02\/01",
  "زمان": "14:26:53",
  "واریز": 3000000000,
  "برداشت": 0,
  "موجودی": 140109763146,
  "شعبه عامل": "کریم خان زند شیراز(308)",
  "شماره سند": 7594592262,
  "نام": "فرشيد",
  "نام خانوادگی": "عزيزي فردخالص",
  "نام پدر": "رمضانعلي",
  "کد ملی": 0,
  "سایر": 0,
  "حساب": 4001003646977
 },
 {
  "شرح": "انتقال وجه از سپرده 700806361773سپرده سرمايه گذاري عادي احمد\/حسن زاده ابنوي\/حاجي به سپرده700831655066 صندوق سرمايه گذاري امين آشنا ايرانيان احد حسن زاده ابنوي2549365895",
  "تاریخ": "1403\/02\/01",
  "زمان": "12:42:55",
  "واریز": 700000000,
  "برداشت": 0,
  "موجودی": 3808763146,
  "شعبه عامل": "پایانه کاراندیش شیراز(315)",
  "شماره سند": 7594128677,
  "نام": "احمد",
  "نام خانوادگی": "حسن زاده ابنوي",
  "نام پدر": "حاجي",
  "کد ملی": "2549365895",
  "سایر": 0,
  "حساب": 700806361773
 },
 {
  "شرح": "انتقال وجه از سپرده 700831655066 صندوق سرمايه گذاري امين آشنا ايرانيان به سپرده7001003510422سپرده سرمايه گذاري عادي صندوق سرمايه گذاري امين آشنا ايرانيان ",
  "تاریخ": "1403\/02\/01",
  "زمان": "15:54:37",
  "واریز": 0,
  "برداشت": 39500000000,
  "موجودی": 35013353146,
  "شعبه عامل": "هاشمیه(447)",
  "شماره سند": 7594876369,
  "نام": "DROPHELL",
  "نام خانوادگی": "DROPHELL",
  "نام پدر": "DROPHELL",
  "کد ملی": "DROPHELL",
  "سایر": "DROPHELL",
  "حساب": 700831655066
 },
 {
  "شرح": "انتقال وجه از سپرده 700831655066 صندوق سرمايه گذاري امين آشنا ايرانيان به سپرده7001003510422سپرده سرمايه گذاري عادي صندوق سرمايه گذاري امين آشنا ايرانيان ",
  "تاریخ": "1403\/02\/01",
  "زمان": "14:57:24",
  "واریز": 0,
  "برداشت": 144700000000,
  "موجودی": 13209363146,
  "شعبه عامل": "هاشمیه(447)",
  "شماره سند": 7594706630,
  "نام": "DROPHELL",
  "نام خانوادگی": "DROPHELL",
  "نام پدر": "DROPHELL",
  "کد ملی": "DROPHELL",
  "سایر": "DROPHELL",
  "حساب": 700831655066
 },
 {
  "شرح": "انتقال وجه از سپرده 700831655066 صندوق سرمايه گذاري امين آشنا ايرانيان به سپرده7001003510422سپرده سرمايه گذاري عادي صندوق سرمايه گذاري امين آشنا ايرانيان ",
  "تاریخ": "1403\/02\/01",
  "زمان": "07:20:42",
  "واریز": 0,
  "برداشت": 113800000000,
  "موجودی": 67443146,
  "شعبه عامل": "هاشمیه(447)",
  "شماره سند": 7592919980,
  "نام": "DROPHELL",
  "نام خانوادگی": "DROPHELL",
  "نام پدر": "DROPHELL",
  "کد ملی": "DROPHELL",
  "سایر": "DROPHELL",
  "حساب": 700831655066
 }
]
}